cred_encryption/__init__.py
cred_encryption/encryption.py
cred_encryption-0.3.0.dist-info/entry_points.txt
cred_encryption-0.3.0.dist-info/WHEEL
cred_encryption-0.3.0.dist-info/METADATA
cred_encryption-0.3.0.dist-info/RECORD
