Metadata-Version: 2.1
Name: cred-encryption
Version: 0.3.0
Summary: 
Home-page: UNKNOWN
License: UNKNOWN
Author: Chris Davies
Author-email: christopher.davies@asg-worldwide.com
Requires-Python: >=3.6,<4.0
Classifier: Programming Language :: Python :: 3
Classifier: Programming Language :: Python :: 3.6
Classifier: Programming Language :: Python :: 3.7
Requires-Dist: cleo (>=0.7.2,<0.8.0)
Requires-Dist: cryptography (>=2.6,<3.0)
